{
  "version": 1,
  "serviceConfiguration": {
    "apiName": "tictactoe",
    "serviceName": "AppSync",
    "gqlSchemaPath": "C:\\Users\\knightrider\\Documents\\tic-tac-toe\\amplify\\backend\\api\\tictactoe\\schema.graphql",
    "defaultAuthType": {
      "mode": "AMAZON_COGNITO_USER_POOLS",
      "cognitoUserPoolId": "authtictactoe1e90a070"
    },
    "conflictResolution": {},
    "additionalAuthTypes": [
      {
        "mode": "API_KEY",
        "expirationTime": 7,
        "apiKeyExpirationDate": "2022-02-01T13:44:08.154Z",
        "keyDescription": "test"
      },
      {
        "mode": "AWS_IAM"
      }
    ]
  }
}